cif_tools/__init__.py
cif_tools/cif_functions.py
cif_tools/draw_kids.py
microwave/SuperSpecCascadeModel_Functions_Test.py
microwave/__init__.py
submm/__init__.py
submm/KIDs/PCA.py
submm/KIDs/PCA_implementation.py
submm/KIDs/__init__.py
submm/KIDs/analyze_multitone.py
submm/KIDs/analyze_single_tone.py
submm/KIDs/calibrate.py
submm/KIDs/disordered_model.py
submm/KIDs/dynes_model.py
submm/KIDs/example_psd_fitting.py
submm/KIDs/find_resonances_interactive.py
submm/KIDs/led_identifier.py
submm/KIDs/noise_theory.py
submm/KIDs/psd_fitting.py
submm/KIDs/res_sweep_tools.py
submm/KIDs/resonance_fitting.py
submm/KIDs/single_tone.py
submm/KIDs/test_fit.py
submm/KIDs/test_single_tone.py
submm/KIDs/KIDShop/__init__.py
submm/KIDs/KIDShop/data_io.py
submm/KIDs/res/__init__.py
submm/KIDs/res/data_io.py
submm/KIDs/res/fit_funcs.py
submm/KIDs/res/fitting.py
submm/KIDs/res/fitting_legacy.py
submm/KIDs/res/multipro.py
submm/KIDs/res/sweep_tools.py
submm/KIDs/res/utils.py
submm/demo/Untitled.ipynb
submm/demo/Untitled1.ipynb
submm/demo/__init__.py
submm/demo/calibrate.ipynb
submm/demo/find_res_and_fit.py
submm/demo/fit_tls.ipynb
submm/demo/fit_tls_demo.py
submm/demo/res_fit.ipynb
submm/demo/res_fit_demo.py
submm/demo/test_fitting.py
submm/instruments/BNC845.py
submm/instruments/NIDAQ.py
submm/instruments/__init__.py
submm/instruments/agilent_E8364A.py
submm/instruments/agilent_e4438c.py
submm/instruments/anritsu.py
submm/instruments/anritsu_mg3691a.py
submm/instruments/anritsu_ms2711d.py
submm/instruments/cryocon22C.py
submm/instruments/hp83732a.py
submm/instruments/scan_chop_lo.py
submm/instruments/weinchel8310.py
submm/lab_brick/__init__.py
submm/lab_brick/core.py
submm/lab_brick/lab-brick-test.py
submm/lab_brick/labbrick_startup.py
submm/multitone_kidPy/__init__.py
submm/multitone_kidPy/analyze.py
submm/multitone_kidPy/analyze_noise.py
submm/multitone_kidPy/read_multitone.py
submm/multitone_mako/__init__.py
submm/multitone_mako/read_multitone.py
submm-0.3.6.dist-info/LICENSE
submm-0.3.6.dist-info/METADATA
submm-0.3.6.dist-info/WHEEL
submm-0.3.6.dist-info/top_level.txt
submm-0.3.6.dist-info/RECORD
