Metadata-Version: 2.1
Name: submm
Version: 0.3.6
Summary: Python routines for submm astronomy instrumentation
Home-page: https://github.com/Wheeler1711/submm_python_routines
Author: Jordan Wheeler
Author-email: wheeler1711@gmail.com
Requires-Python: >3.7
License-File: LICENSE
Requires-Dist: numpy
Requires-Dist: matplotlib >=3.5.2
Requires-Dist: scipy
Requires-Dist: numba
Requires-Dist: tqdm
Requires-Dist: importlib-metadata
Requires-Dist: toml
